sphinxcontrib_friendlinks/__init__.py
sphinxcontrib_friendlinks/directives.py
sphinxcontrib_friendlinks/nodes.py
sphinxcontrib_friendlinks/static/friendlinks.css
sphinxcontrib_friendlinks/writers.py
sphinxcontrib_friendlinks-0.1.2.dist-info/WHEEL
sphinxcontrib_friendlinks-0.1.2.dist-info/METADATA
sphinxcontrib_friendlinks-0.1.2.dist-info/RECORD
