Metadata-Version: 2.3
Name: sphinxcontrib-friendlinks
Version: 0.1.2
Summary: A Sphinx extension for rendering beautiful friend link cards
Keywords: sphinx,sphinx-extension,friendlinks,blogroll,documentation
Author: un4gt
Author-email: un4gt <mt3085570450@outlook.com>
License: MIT
Classifier: Development Status :: 3 - Alpha
Classifier: Framework :: Sphinx
Classifier: Framework :: Sphinx :: Extension
Classifier: Intended Audience :: Developers
Classifier: License :: OSI Approved :: MIT License
Classifier: Operating System :: OS Independent
Classifier: Programming Language :: Python :: 3
Classifier: Programming Language :: Python :: 3.8
Classifier: Programming Language :: Python :: 3.9
Classifier: Programming Language :: Python :: 3.10
Classifier: Programming Language :: Python :: 3.11
Classifier: Programming Language :: Python :: 3.12
Classifier: Programming Language :: Python :: 3.13
Classifier: Topic :: Documentation
Classifier: Topic :: Documentation :: Sphinx
Requires-Dist: sphinx>=7.1.2
Maintainer: un4gt
Maintainer-email: un4gt <mt3085570450@outlook.com>
Requires-Python: >=3.8
Project-URL: Homepage, https://github.com/un4gt/sphinxcontrib-friendlinks
Project-URL: Issues, https://github.com/un4gt/sphinxcontrib-friendlinks/issues
Project-URL: Repository, https://github.com/un4gt/sphinxcontrib-friendlinks
